tf_pydf/__init__.py
tf_pydf/tf_idf.py
tf_pydf-0.1.0.dist-info/LICENSE
tf_pydf-0.1.0.dist-info/METADATA
tf_pydf-0.1.0.dist-info/WHEEL
tf_pydf-0.1.0.dist-info/RECORD
