Metadata-Version: 2.1
Name: tf-pydf
Version: 0.1.0
Summary: A simple implimentation of TF-IDF
License: MIT
Author: Edvinas Adomaitis
Author-email: edvinasad7@gmail.com
Requires-Python: >=3.10,<4.0
Classifier: License :: OSI Approved :: MIT License
Classifier: Programming Language :: Python :: 3
Classifier: Programming Language :: Python :: 3.10
Classifier: Programming Language :: Python :: 3.11
